[
  {
    "id": 1,
    "name": "Овен",
    "period": "21 марта - 19 апреля",
    "icon": ""
  },
  {
    "id": 2,
    "name": "Телец",
    "period": "20 апреля - 20 мая",
    "icon": ""
  },
  {
    "id": 3,
    "name": "Близнецы",
    "period": "21 мая - 20 июня",
    "icon": ""
  },
  {
    "id": 4,
    "name": "Рак",
    "period": "21 июня - 22 июля",
    "icon": ""
  },
  {
    "id": 5,
    "name": "Лев",
    "period": "23 июля - 22 августа",
    "icon": ""
  },
  {
    "id": 6,
    "name": "Дева",
    "period": "23 августа - 22 сентября",
    "icon": ""
  },
  {
    "id": 7,
    "name": "Весы",
    "period": "23 сентября - 22 октября",
    "icon": ""
  },
  {
    "id": 8,
    "name": "Скорпион",
    "period": "23 октября - 21 ноября",
    "icon": ""
  },
  {
    "id": 9,
    "name": "Стрелец",
    "period": "22 ноября - 21 декабря",
    "icon": ""
  },
  {
    "id": 10,
    "name": "Козерог",
    "period": "22 декабря - 19 января",
    "icon": ""
  },
  {
    "id": 11,
    "name": "Водолей",
    "period": "20 января - 18 февраля",
    "icon": ""
  },
  {
    "id": 12,
    "name": "Рыбы",
    "period": "19 февраля - 20 марта",
    "icon": ""
  }
]
